neon_iris/__init__.py
neon_iris/cli.py
neon_iris/client.py
neon_iris/llm.py
neon_iris/util.py
neon_iris/version.py
neon_iris/voice_client.py
neon_iris/web_client.py
neon_iris-0.1.0.dist-info/LICENSE.md
neon_iris-0.1.0.dist-info/METADATA
neon_iris-0.1.0.dist-info/WHEEL
neon_iris-0.1.0.dist-info/entry_points.txt
neon_iris-0.1.0.dist-info/top_level.txt
neon_iris-0.1.0.dist-info/RECORD
