Metadata-Version: 2.1
Name: neon-iris
Version: 0.1.0
Summary: Interactive Relay for Intelligence Systems
Home-page: https://github.com/neongeckocom/neon-iris
Author: Neongecko
Author-email: developers@neon.ai
License: BSD-3-Clause
Classifier: Programming Language :: Python :: 3
Classifier: Operating System :: OS Independent
Requires-Python: >=3.6
License-File: LICENSE.md
Requires-Dist: click ~=8.0
Requires-Dist: click-default-group ~=1.2
Requires-Dist: neon-utils ~=1.0
Requires-Dist: pyyaml <7.0.0,>=5.4
Requires-Dist: neon-mq-connector >=0.7.1,~=0.7
Requires-Dist: ovos-bus-client ~=0.0.3
Provides-Extra: gradio
Requires-Dist: gradio ~=3.28 ; extra == 'gradio'
Requires-Dist: librosa ~=0.9 ; extra == 'gradio'
Requires-Dist: soundfile ~=0.12 ; extra == 'gradio'
